{
  "whitelist": ["pulpxi", "Meku45", "kriscrosaplesauc", "rip_oceanicfan", "Peak2000", "TheCouncilOf_8", "2C0LD9469", "Orion_258", "Hstar747", "Neo_320YT_TV", "EvilVoli"],
  "whitelistMessage": "You're not on the playtest whitelist. DM the creator on Discord if it is a mistake!",
  "_default": {
    "active": false,
    "message": "This playtest version has expired. If you think this is a mistake, please contact the creator."
  },
  "0.3.7-playtest": {
    "active": true,
    "message": "Hi! The playtest is live - have fun! Report bugs in #playtesting-feedback or the form.",
    "inactiveMessage": "The playtest isn't live yet - hang tight!",
  },
  "0.3.7-gate": {
    "active": true,
    "message": "Hi! Artist-Build! Report bugs in #playtesting-feedback or the form.",
    "inactiveMessage": "Build not active!",
  }
}
